[{"keyword":"Feature","type":"feature","description":"","line":1,"name":"Automation Practise","uri":"F:\\VS Code projects\\Webdriverio\\Ex_1\\features\\AutomationPractise.feature","tags":[],"elements":[{"keyword":"Scenario","type":"scenario","description":"","name":"Seach an item","tags":[],"id":"automation-practise;seach-an-item","steps":[{"arguments":[],"keyword":"Before","name":"","result":{"status":"passed","duration":1000000},"line":null,"match":{"location":"can not be determined with webdriver.io"}},{"arguments":[],"keyword":"Given","name":"the user navigates to the home page","result":{"status":"passed","duration":13583000000},"line":null,"match":{"location":"can not be determined with webdriver.io"}},{"arguments":[],"keyword":"When","name":"the user enters \"blouse\" in the search bar","result":{"status":"passed","duration":3189000000},"line":null,"match":{"location":"can not be determined with webdriver.io"}},{"arguments":[],"keyword":"Then","name":"the user verify the item is \"blouse\" state","result":{"status":"failed","duration":10045000000,"error_message":"Error: Expect Blouse to have text\n\nExpected: \"blouse\"\nReceived: undefined\n    at World.<anonymous> (F:\\VS Code projects\\Webdriverio\\Ex_1\\features\\step-definitions\\/then.js:15:27)\n    at processTicksAndRejections (node:internal/process/task_queues:96:5)"},"line":null,"match":{"location":"can not be determined with webdriver.io"}},{"arguments":[],"keyword":"After","name":"","result":{"status":"passed","duration":1000000},"line":null,"match":{"location":"can not be determined with webdriver.io"}}]}],"id":"automation-practise","metadata":{"browser":{"name":"chrome","version":"101.0.4951.54"},"device":"Device name not known","platform":{"name":"windows","version":"Version not known"}}}]
